{
  "objects": [
    {
      "pixel_coords": [
        109,
        85,
        12.776400566101074
      ],
      "shape": "sphere",
      "3d_coords": [
        -2.4830639362335205,
        -0.23956866562366486,
        0.5249999761581421
      ],
      "color": "red",
      "size": "medium",
      "rotation": 53.24145803852774,
      "material": "rubber"
    },
    {
      "pixel_coords": [
        149,
        113,
        10.926815032958984
      ],
      "shape": "cylinder",
      "3d_coords": [
        0.10904135555028915,
        -0.5806478261947632,
        0.5249999761581421
      ],
      "color": "red",
      "size": "medium",
      "rotation": 133.21954543594188,
      "material": "rubber"
    },
    {
      "pixel_coords": [
        168,
        58,
        14.724989891052246
      ],
      "shape": "sphere",
      "3d_coords": [
        -2.736619234085083,
        2.958848476409912,
        0.699999988079071
      ],
      "color": "red",
      "size": "large",
      "rotation": 58.04690036596716,
      "material": "rubber"
    },
    {
      "pixel_coords": [
        69,
        99,
        11.393685340881348
      ],
      "shape": "sphere",
      "3d_coords": [
        -2.124908924102783,
        -2.059805393218994,
        0.699999988079071
      ],
      "color": "red",
      "size": "large",
      "rotation": 52.07262543364112,
      "material": "rubber"
    },
    {
      "pixel_coords": [
        236,
        126,
        10.591444969177246
      ],
      "shape": "cube",
      "3d_coords": [
        2.271914482116699,
        1.0456664562225342,
        0.3499999940395355
      ],
      "color": "red",
      "size": "small",
      "rotation": 154.64769338408013,
      "material": "rubber"
    },
    {
      "pixel_coords": [
        199,
        69,
        13.601198196411133
      ],
      "shape": "cube",
      "3d_coords": [
        -0.9778121709823608,
        2.9512217044830322,
        0.699999988079071
      ],
      "color": "red",
      "size": "large",
      "rotation": 329.82899250040884,
      "material": "rubber"
    }
  ],
  "directions": {
    "front": [
      0.754490315914154,
      -0.6563112735748291,
      -0.0
    ],
    "right": [
      0.6563112735748291,
      0.7544902563095093,
      -0.0
    ],
    "below": [
      -0.0,
      -0.0,
      -1.0
    ],
    "behind": [
      -0.754490315914154,
      0.6563112735748291,
      0.0
    ],
    "above": [
      0.0,
      0.0,
      1.0
    ],
    "left": [
      -0.6563112735748291,
      -0.7544902563095093,
      0.0
    ]
  },
  "image_index": 86,
  "split": "new",
  "relationships": {
    "front": [
      [
        1,
        3,
        4
      ],
      [
        4
      ],
      [
        0,
        1,
        3,
        4,
        5
      ],
      [
        1,
        4
      ],
      [],
      [
        0,
        1,
        3,
        4
      ]
    ],
    "right": [
      [
        1,
        2,
        4,
        5
      ],
      [
        2,
        4,
        5
      ],
      [
        4,
        5
      ],
      [
        0,
        1,
        2,
        4,
        5
      ],
      [],
      [
        4
      ]
    ],
    "behind": [
      [
        2,
        5
      ],
      [
        0,
        2,
        3,
        5
      ],
      [],
      [
        0,
        2,
        5
      ],
      [
        0,
        1,
        2,
        3,
        5
      ],
      [
        2
      ]
    ],
    "left": [
      [
        3
      ],
      [
        0,
        3
      ],
      [
        0,
        1,
        3
      ],
      [],
      [
        0,
        1,
        2,
        3,
        5
      ],
      [
        0,
        1,
        2,
        3
      ]
    ]
  },
  "intruder_pos": [
    199,
    69,
    13.601198196411133
  ],
  "image_filename": "CLEVR_new_000086.png"
}