{
  "image_index": 642,
  "image_filename": "CLEVR_new_000642.png",
  "relationships": {
    "left": [
      [
        3,
        4,
        5,
        7
      ],
      [
        0,
        2,
        3,
        4,
        5,
        6,
        7
      ],
      [
        0,
        3,
        4,
        5,
        7
      ],
      [
        4,
        7
      ],
      [],
      [
        3,
        4,
        7
      ],
      [
        0,
        2,
        3,
        4,
        5,
        7
      ],
      [
        4
      ]
    ],
    "front": [
      [
        3,
        5,
        6,
        7
      ],
      [
        0,
        3,
        4,
        5,
        6,
        7
      ],
      [
        0,
        1,
        3,
        4,
        5,
        6,
        7
      ],
      [
        5,
        6,
        7
      ],
      [
        0,
        3,
        5,
        6,
        7
      ],
      [],
      [
        5
      ],
      [
        5,
        6
      ]
    ],
    "behind": [
      [
        1,
        2,
        4
      ],
      [
        2
      ],
      [],
      [
        0,
        1,
        2,
        4
      ],
      [
        1,
        2
      ],
      [
        0,
        1,
        2,
        3,
        4,
        6,
        7
      ],
      [
        0,
        1,
        2,
        3,
        4,
        7
      ],
      [
        0,
        1,
        2,
        3,
        4
      ]
    ],
    "right": [
      [
        1,
        2,
        6
      ],
      [],
      [
        1,
        6
      ],
      [
        0,
        1,
        2,
        5,
        6
      ],
      [
        0,
        1,
        2,
        3,
        5,
        6,
        7
      ],
      [
        0,
        1,
        2,
        6
      ],
      [
        1
      ],
      [
        0,
        1,
        2,
        3,
        5,
        6
      ]
    ]
  },
  "objects": [
    {
      "pixel_coords": [
        163,
        107,
        11.09028434753418
      ],
      "shape": "sphere",
      "3d_coords": [
        0.12289518117904663,
        0.03947622701525688,
        0.5249999761581421
      ],
      "color": "red",
      "material": "rubber",
      "rotation": 50.76533638699733,
      "size": "medium"
    },
    {
      "pixel_coords": [
        250,
        88,
        11.92427921295166
      ],
      "shape": "sphere",
      "3d_coords": [
        1.17106294631958,
        2.9844274520874023,
        0.699999988079071
      ],
      "color": "red",
      "material": "rubber",
      "rotation": 327.25925085912104,
      "size": "large"
    },
    {
      "pixel_coords": [
        184,
        75,
        13.830048561096191
      ],
      "shape": "cube",
      "3d_coords": [
        -1.6998649835586548,
        2.6298060417175293,
        0.3499999940395355
      ],
      "color": "red",
      "material": "rubber",
      "rotation": 117.73503935492764,
      "size": "small"
    },
    {
      "pixel_coords": [
        114,
        117,
        10.521302223205566
      ],
      "shape": "cylinder",
      "3d_coords": [
        -0.32281145453453064,
        -1.5346442461013794,
        0.5249999761581421
      ],
      "color": "red",
      "material": "rubber",
      "rotation": 136.66462173540523,
      "size": "medium"
    },
    {
      "pixel_coords": [
        51,
        97,
        11.704145431518555
      ],
      "shape": "sphere",
      "3d_coords": [
        -2.806907892227173,
        -2.4150054454803467,
        0.5249999761581421
      ],
      "color": "red",
      "material": "rubber",
      "rotation": 311.1288735744435,
      "size": "medium"
    },
    {
      "pixel_coords": [
        129,
        149,
        8.726439476013184
      ],
      "shape": "cube",
      "3d_coords": [
        1.5890934467315674,
        -2.3035426139831543,
        0.699999988079071
      ],
      "color": "red",
      "material": "rubber",
      "rotation": 322.4974514002283,
      "size": "large"
    },
    {
      "pixel_coords": [
        206,
        147,
        9.12362289428711
      ],
      "shape": "cube",
      "3d_coords": [
        2.5702426433563232,
        -0.5457906723022461,
        0.5249999761581421
      ],
      "color": "red",
      "material": "rubber",
      "rotation": 222.783773587678,
      "size": "medium"
    },
    {
      "pixel_coords": [
        82,
        138,
        9.826539993286133
      ],
      "shape": "cube",
      "3d_coords": [
        -0.12904661893844604,
        -2.7150447368621826,
        0.3499999940395355
      ],
      "color": "red",
      "material": "rubber",
      "rotation": 22.534549908720862,
      "size": "small"
    }
  ],
  "intruder_pos": [
    82,
    138,
    9.826539993286133
  ],
  "split": "new",
  "directions": {
    "above": [
      0.0,
      0.0,
      1.0
    ],
    "below": [
      -0.0,
      -0.0,
      -1.0
    ],
    "left": [
      -0.6563112735748291,
      -0.7544902563095093,
      0.0
    ],
    "behind": [
      -0.754490315914154,
      0.6563112735748291,
      0.0
    ],
    "front": [
      0.754490315914154,
      -0.6563112735748291,
      -0.0
    ],
    "right": [
      0.6563112735748291,
      0.7544902563095093,
      -0.0
    ]
  }
}