{
  "image_index": 592,
  "image_filename": "CLEVR_new_000592.png",
  "relationships": {
    "left": [
      [
        1,
        2,
        3,
        4,
        5
      ],
      [
        4
      ],
      [
        1,
        4
      ],
      [
        1,
        2,
        4
      ],
      [],
      [
        1,
        2,
        3,
        4
      ]
    ],
    "front": [
      [
        1,
        2,
        4,
        5
      ],
      [],
      [
        1,
        5
      ],
      [
        0,
        1,
        2,
        4,
        5
      ],
      [
        1,
        2,
        5
      ],
      [
        1
      ]
    ],
    "behind": [
      [
        3
      ],
      [
        0,
        2,
        3,
        4,
        5
      ],
      [
        0,
        3,
        4
      ],
      [],
      [
        0,
        3
      ],
      [
        0,
        2,
        3,
        4
      ]
    ],
    "right": [
      [],
      [
        0,
        2,
        3,
        5
      ],
      [
        0,
        3,
        5
      ],
      [
        0,
        5
      ],
      [
        0,
        1,
        2,
        3,
        5
      ],
      [
        0
      ]
    ]
  },
  "objects": [
    {
      "pixel_coords": [
        260,
        91,
        11.360265731811523
      ],
      "shape": "cylinder",
      "3d_coords": [
        1.6096912622451782,
        2.905991554260254,
        0.699999988079071
      ],
      "color": "blue",
      "material": "rubber",
      "rotation": 204.7271657741845,
      "size": "large"
    },
    {
      "pixel_coords": [
        158,
        149,
        8.785030364990234
      ],
      "shape": "cylinder",
      "3d_coords": [
        1.7631685733795166,
        -1.5786457061767578,
        0.3499999940395355
      ],
      "color": "green",
      "material": "rubber",
      "rotation": 226.20252651478205,
      "size": "small"
    },
    {
      "pixel_coords": [
        179,
        115,
        10.550373077392578
      ],
      "shape": "cylinder",
      "3d_coords": [
        0.6811257004737854,
        0.18260759115219116,
        0.3499999940395355
      ],
      "color": "red",
      "material": "rubber",
      "rotation": 65.09746643841274,
      "size": "small"
    },
    {
      "pixel_coords": [
        201,
        84,
        12.42249584197998
      ],
      "shape": "cylinder",
      "3d_coords": [
        -0.3930157721042633,
        2.267970561981201,
        0.5249999761581421
      ],
      "color": "blue",
      "material": "rubber",
      "rotation": 194.4319142021696,
      "size": "medium"
    },
    {
      "pixel_coords": [
        84,
        108,
        11.05320930480957
      ],
      "shape": "cylinder",
      "3d_coords": [
        -1.6848584413528442,
        -1.6985762119293213,
        0.3499999940395355
      ],
      "color": "blue",
      "material": "rubber",
      "rotation": 135.40385173135772,
      "size": "small"
    },
    {
      "pixel_coords": [
        242,
        122,
        9.744760513305664
      ],
      "shape": "cylinder",
      "3d_coords": [
        2.414328098297119,
        0.9467096328735352,
        0.5249999761581421
      ],
      "color": "blue",
      "material": "rubber",
      "rotation": 238.11435431476298,
      "size": "medium"
    }
  ],
  "intruder_pos": [
    242,
    122,
    9.744760513305664
  ],
  "split": "new",
  "directions": {
    "above": [
      0.0,
      0.0,
      1.0
    ],
    "below": [
      -0.0,
      -0.0,
      -1.0
    ],
    "left": [
      -0.6563112735748291,
      -0.7544902563095093,
      0.0
    ],
    "behind": [
      -0.754490315914154,
      0.6563112735748291,
      0.0
    ],
    "front": [
      0.754490315914154,
      -0.6563112735748291,
      -0.0
    ],
    "right": [
      0.6563112735748291,
      0.7544902563095093,
      -0.0
    ]
  }
}