{
  "directions": {
    "below": [
      -0.0,
      -0.0,
      -1.0
    ],
    "right": [
      0.6563112735748291,
      0.7544902563095093,
      -0.0
    ],
    "front": [
      0.754490315914154,
      -0.6563112735748291,
      -0.0
    ],
    "behind": [
      -0.754490315914154,
      0.6563112735748291,
      0.0
    ],
    "above": [
      0.0,
      0.0,
      1.0
    ],
    "left": [
      -0.6563112735748291,
      -0.7544902563095093,
      0.0
    ]
  },
  "objects": [
    {
      "color": "yellow",
      "size": "small",
      "rotation": 243.42354501929302,
      "shape": "sphere",
      "material": "metal",
      "pixel_coords": [
        125,
        114,
        10.480162620544434
      ],
      "3d_coords": [
        -0.4416002035140991,
        -0.9776688814163208,
        0.3499999940395355
      ]
    },
    {
      "color": "blue",
      "size": "small",
      "rotation": 202.55607932311432,
      "shape": "sphere",
      "material": "metal",
      "pixel_coords": [
        196,
        105,
        11.048758506774902
      ],
      "3d_coords": [
        0.43594858050346375,
        1.1102927923202515,
        0.3499999940395355
      ]
    },
    {
      "color": "brown",
      "size": "large",
      "rotation": 202.9654693667033,
      "shape": "cylinder",
      "material": "rubber",
      "pixel_coords": [
        156,
        64,
        13.309216499328613
      ],
      "3d_coords": [
        -2.537614583969116,
        1.872257947921753,
        0.699999988079071
      ]
    },
    {
      "color": "purple",
      "size": "large",
      "rotation": 156.8318568891605,
      "shape": "sphere",
      "material": "metal",
      "pixel_coords": [
        167,
        119,
        9.502301216125488
      ],
      "3d_coords": [
        1.053692102432251,
        -0.6159841418266296,
        0.699999988079071
      ]
    },
    {
      "color": "purple",
      "size": "large",
      "rotation": 198.38196295309126,
      "shape": "cylinder",
      "material": "metal",
      "pixel_coords": [
        239,
        81,
        11.790919303894043
      ],
      "3d_coords": [
        0.5999801158905029,
        2.9498555660247803,
        0.699999988079071
      ]
    },
    {
      "color": "red",
      "size": "small",
      "rotation": 127.70114865541241,
      "shape": "cube",
      "material": "rubber",
      "pixel_coords": [
        62,
        97,
        11.54810619354248
      ],
      "3d_coords": [
        -2.779660224914551,
        -1.8948068618774414,
        0.3499999940395355
      ]
    }
  ],
  "image_index": 150,
  "split": "new",
  "relationships": {
    "right": [
      [
        1,
        2,
        3,
        4
      ],
      [
        4
      ],
      [
        1,
        3,
        4
      ],
      [
        1,
        4
      ],
      [],
      [
        0,
        1,
        2,
        3,
        4
      ]
    ],
    "front": [
      [
        3
      ],
      [
        0,
        3
      ],
      [
        0,
        1,
        3,
        4,
        5
      ],
      [],
      [
        0,
        1,
        3,
        5
      ],
      [
        0,
        1,
        3
      ]
    ],
    "behind": [
      [
        1,
        2,
        4,
        5
      ],
      [
        2,
        4,
        5
      ],
      [],
      [
        0,
        1,
        2,
        4,
        5
      ],
      [
        2
      ],
      [
        2,
        4
      ]
    ],
    "left": [
      [
        5
      ],
      [
        0,
        2,
        3,
        5
      ],
      [
        0,
        5
      ],
      [
        0,
        2,
        5
      ],
      [
        0,
        1,
        2,
        3,
        5
      ],
      []
    ]
  },
  "image_filename": "CLEVR_new_000150.png",
  "red_cube_pos": [
    [
      46,
      128
    ],
    [
      76,
      157
    ]
  ]
}