{
  "image_index": 1166,
  "relationships": {
    "right": [
      [
        2,
        3
      ],
      [
        0,
        2,
        3
      ],
      [],
      [
        2
      ],
      [
        0,
        1,
        2,
        3,
        5,
        7
      ],
      [
        0,
        1,
        2,
        3
      ],
      [
        0,
        1,
        2,
        3,
        4,
        5,
        7
      ],
      [
        0,
        1,
        2,
        3,
        5
      ]
    ],
    "front": [
      [
        5
      ],
      [
        0,
        4,
        5
      ],
      [
        0,
        1,
        4,
        5,
        7
      ],
      [
        0,
        1,
        2,
        4,
        5,
        6,
        7
      ],
      [
        0,
        5
      ],
      [],
      [
        0,
        1,
        2,
        4,
        5,
        7
      ],
      [
        0,
        1,
        4,
        5
      ]
    ],
    "behind": [
      [
        1,
        2,
        3,
        4,
        6,
        7
      ],
      [
        2,
        3,
        6,
        7
      ],
      [
        3,
        6
      ],
      [],
      [
        1,
        2,
        3,
        6,
        7
      ],
      [
        0,
        1,
        2,
        3,
        4,
        6,
        7
      ],
      [
        3
      ],
      [
        2,
        3,
        6
      ]
    ],
    "left": [
      [
        1,
        4,
        5,
        6,
        7
      ],
      [
        4,
        5,
        6,
        7
      ],
      [
        0,
        1,
        3,
        4,
        5,
        6,
        7
      ],
      [
        0,
        1,
        4,
        5,
        6,
        7
      ],
      [
        6
      ],
      [
        4,
        6,
        7
      ],
      [],
      [
        4,
        6
      ]
    ]
  },
  "directions": {
    "right": [
      0.6563112735748291,
      0.7544902563095093,
      -0.0
    ],
    "front": [
      0.754490315914154,
      -0.6563112735748291,
      -0.0
    ],
    "behind": [
      -0.754490315914154,
      0.6563112735748291,
      0.0
    ],
    "above": [
      0.0,
      0.0,
      1.0
    ],
    "below": [
      -0.0,
      -0.0,
      -1.0
    ],
    "left": [
      -0.6563112735748291,
      -0.7544902563095093,
      0.0
    ]
  },
  "red_cube_pos": [
    [
      105,
      116
    ],
    [
      129,
      143
    ]
  ],
  "image_filename": "CLEVR_new_001166.png",
  "split": "new",
  "objects": [
    {
      "size": "large",
      "pixel_coords": [
        189,
        148,
        8.835701942443848
      ],
      "color": "purple",
      "material": "metal",
      "rotation": 132.075930486531,
      "3d_coords": [
        2.444669723510742,
        -1.0498777627944946,
        0.699999988079071
      ],
      "shape": "cube"
    },
    {
      "size": "small",
      "pixel_coords": [
        166,
        120,
        10.684972763061523
      ],
      "color": "yellow",
      "material": "rubber",
      "rotation": 338.9376538156603,
      "3d_coords": [
        0.5974245071411133,
        -0.24310845136642456,
        0.3499999940395355
      ],
      "shape": "cube"
    },
    {
      "size": "small",
      "pixel_coords": [
        236,
        101,
        11.798190116882324
      ],
      "color": "yellow",
      "material": "metal",
      "rotation": 351.405464570294,
      "3d_coords": [
        1.0777608156204224,
        2.4117283821105957,
        0.3499999940395355
      ],
      "shape": "sphere"
    },
    {
      "size": "large",
      "pixel_coords": [
        220,
        76,
        12.715353965759277
      ],
      "color": "gray",
      "material": "metal",
      "rotation": 307.7811809308417,
      "3d_coords": [
        -0.15376527607440948,
        2.9174656867980957,
        0.699999988079071
      ],
      "shape": "cube"
    },
    {
      "size": "large",
      "pixel_coords": [
        78,
        135,
        9.366118431091309
      ],
      "color": "brown",
      "material": "rubber",
      "rotation": 150.34531136005828,
      "3d_coords": [
        0.14040876924991608,
        -2.9183807373046875,
        0.699999988079071
      ],
      "shape": "cube"
    },
    {
      "size": "large",
      "pixel_coords": [
        122,
        164,
        8.278536796569824
      ],
      "color": "brown",
      "material": "metal",
      "rotation": 84.80753763877354,
      "3d_coords": [
        1.9246881008148193,
        -2.7244527339935303,
        0.699999988079071
      ],
      "shape": "sphere"
    },
    {
      "size": "large",
      "pixel_coords": [
        82,
        81,
        12.352897644042969
      ],
      "color": "gray",
      "material": "metal",
      "rotation": 233.2160407192864,
      "3d_coords": [
        -2.920799732208252,
        -1.1762725114822388,
        0.699999988079071
      ],
      "shape": "cylinder"
    },
    {
      "size": "small",
      "pixel_coords": [
        118,
        110,
        11.248394012451172
      ],
      "color": "red",
      "material": "rubber",
      "rotation": 85.69290967083941,
      "3d_coords": [
        -0.8706226348876953,
        -1.0161274671554565,
        0.3499999940395355
      ],
      "shape": "cube"
    }
  ]
}