{
  "relationships": {
    "left": [
      [
        2,
        4,
        7
      ],
      [
        0,
        2,
        3,
        4,
        5,
        6,
        7
      ],
      [],
      [
        0,
        2,
        4,
        7
      ],
      [
        2,
        7
      ],
      [
        0,
        2,
        3,
        4,
        7
      ],
      [
        0,
        2,
        3,
        4,
        5,
        7
      ],
      [
        2
      ]
    ],
    "right": [
      [
        1,
        3,
        5,
        6
      ],
      [],
      [
        0,
        1,
        3,
        4,
        5,
        6,
        7
      ],
      [
        1,
        5,
        6
      ],
      [
        0,
        1,
        3,
        5,
        6
      ],
      [
        1,
        6
      ],
      [
        1
      ],
      [
        0,
        1,
        3,
        4,
        5,
        6
      ]
    ],
    "behind": [
      [
        1,
        2,
        3,
        5,
        6
      ],
      [
        3,
        5,
        6
      ],
      [
        1,
        3,
        5,
        6
      ],
      [
        5,
        6
      ],
      [
        0,
        1,
        2,
        3,
        5,
        6,
        7
      ],
      [],
      [
        5
      ],
      [
        0,
        1,
        2,
        3,
        5,
        6
      ]
    ],
    "front": [
      [
        4,
        7
      ],
      [
        0,
        2,
        4,
        7
      ],
      [
        0,
        4,
        7
      ],
      [
        0,
        1,
        2,
        4,
        7
      ],
      [],
      [
        0,
        1,
        2,
        3,
        4,
        6,
        7
      ],
      [
        0,
        1,
        2,
        3,
        4,
        7
      ],
      [
        4
      ]
    ]
  },
  "split": "new",
  "objects": [
    {
      "rotation": 201.92987468999266,
      "shape": "sphere",
      "color": "brown",
      "pixel_coords": [
        139,
        126,
        9.827611923217773
      ],
      "material": "rubber",
      "3d_coords": [
        0.3640548288822174,
        -1.1504509449005127,
        0.3499999940395355
      ],
      "size": "small"
    },
    {
      "rotation": 356.7880010024598,
      "shape": "cube",
      "color": "purple",
      "pixel_coords": [
        246,
        97,
        10.802441596984863
      ],
      "material": "metal",
      "3d_coords": [
        1.6679133176803589,
        2.0659914016723633,
        0.699999988079071
      ],
      "size": "large"
    },
    {
      "rotation": 145.08965920520217,
      "shape": "cube",
      "color": "blue",
      "pixel_coords": [
        51,
        118,
        10.291015625
      ],
      "material": "metal",
      "3d_coords": [
        -1.8230149745941162,
        -2.6978349685668945,
        0.3499999940395355
      ],
      "size": "small"
    },
    {
      "rotation": 68.2314994331071,
      "shape": "cylinder",
      "color": "brown",
      "pixel_coords": [
        158,
        83,
        11.864934921264648
      ],
      "material": "rubber",
      "3d_coords": [
        -1.070742130279541,
        0.9132322669029236,
        0.699999988079071
      ],
      "size": "large"
    },
    {
      "rotation": 249.42637265543095,
      "shape": "sphere",
      "color": "red",
      "pixel_coords": [
        118,
        157,
        8.414627075195312
      ],
      "material": "rubber",
      "3d_coords": [
        1.2250916957855225,
        -2.54414701461792,
        0.3499999940395355
      ],
      "size": "small"
    },
    {
      "rotation": 354.7245540649162,
      "shape": "cylinder",
      "color": "green",
      "pixel_coords": [
        188,
        76,
        13.505119323730469
      ],
      "material": "rubber",
      "3d_coords": [
        -1.4880133867263794,
        2.886136293411255,
        0.3499999940395355
      ],
      "size": "small"
    },
    {
      "rotation": 191.41544624860603,
      "shape": "sphere",
      "color": "brown",
      "pixel_coords": [
        217,
        75,
        12.543102264404297
      ],
      "material": "metal",
      "3d_coords": [
        -0.15342479944229126,
        2.9824206829071045,
        0.699999988079071
      ],
      "size": "large"
    },
    {
      "rotation": 275.9898380446145,
      "shape": "cube",
      "color": "red",
      "pixel_coords": [
        72,
        137,
        9.249943733215332
      ],
      "material": "rubber",
      "3d_coords": [
        -0.372866690158844,
        -2.866215467453003,
        0.3499999940395355
      ],
      "size": "small"
    }
  ],
  "red_cube_pos": [
    [
      56,
      84
    ],
    [
      86,
      120
    ]
  ],
  "image_index": 1507,
  "directions": {
    "left": [
      -0.6563112735748291,
      -0.7544902563095093,
      0.0
    ],
    "below": [
      -0.0,
      -0.0,
      -1.0
    ],
    "behind": [
      -0.754490315914154,
      0.6563112735748291,
      0.0
    ],
    "right": [
      0.6563112735748291,
      0.7544902563095093,
      -0.0
    ],
    "front": [
      0.754490315914154,
      -0.6563112735748291,
      -0.0
    ],
    "above": [
      0.0,
      0.0,
      1.0
    ]
  },
  "image_filename": "CLEVR_new_001507.png"
}