{
  "intruder_pos": [
    [
      146,
      117
    ],
    [
      190,
      164
    ]
  ],
  "relationships": {
    "left": [
      [
        1,
        4
      ],
      [],
      [
        0,
        1,
        3,
        4,
        5
      ],
      [
        0,
        1,
        4,
        5
      ],
      [
        1
      ],
      [
        0,
        1,
        4
      ]
    ],
    "right": [
      [
        2,
        3,
        5
      ],
      [
        0,
        2,
        3,
        4,
        5
      ],
      [],
      [
        2
      ],
      [
        0,
        2,
        3,
        5
      ],
      [
        2,
        3
      ]
    ],
    "behind": [
      [
        1,
        2,
        3,
        4,
        5
      ],
      [
        3,
        4,
        5
      ],
      [
        1,
        3,
        4,
        5
      ],
      [],
      [
        3
      ],
      [
        3,
        4
      ]
    ],
    "front": [
      [],
      [
        0,
        2
      ],
      [
        0
      ],
      [
        0,
        1,
        2,
        4,
        5
      ],
      [
        0,
        1,
        2,
        5
      ],
      [
        0,
        1,
        2
      ]
    ]
  },
  "split": "new",
  "objects": [
    {
      "shape": "cylinder",
      "3d_coords": [
        1.7708696126937866,
        -2.6581649780273438,
        0.3499999940395355
      ],
      "material": "rubber",
      "color": "green",
      "size": "small",
      "rotation": 298.6750358627233,
      "pixel_coords": [
        120,
        171,
        7.71186637878418
      ]
    },
    {
      "shape": "sphere",
      "3d_coords": [
        -1.6976654529571533,
        -2.0623207092285156,
        0.699999988079071
      ],
      "material": "rubber",
      "color": "green",
      "size": "large",
      "rotation": 147.182619618145,
      "pixel_coords": [
        69,
        99,
        10.228832244873047
      ]
    },
    {
      "shape": "cylinder",
      "3d_coords": [
        2.9505677223205566,
        0.20833785831928253,
        0.3499999940395355
      ],
      "material": "rubber",
      "color": "green",
      "size": "small",
      "rotation": 259.53788271427896,
      "pixel_coords": [
        244,
        148,
        8.547066688537598
      ]
    },
    {
      "shape": "cube",
      "3d_coords": [
        -1.3528826236724854,
        2.140883684158325,
        0.5249999761581421
      ],
      "material": "rubber",
      "color": "green",
      "size": "medium",
      "rotation": 18.95641242656898,
      "pixel_coords": [
        181,
        75,
        12.47077465057373
      ]
    },
    {
      "shape": "cube",
      "3d_coords": [
        -1.5519758462905884,
        -0.4168643653392792,
        0.5249999761581421
      ],
      "material": "rubber",
      "color": "green",
      "size": "medium",
      "rotation": 84.90984432630198,
      "pixel_coords": [
        119,
        92,
        11.149221420288086
      ]
    },
    {
      "shape": "cube",
      "3d_coords": [
        -0.17646528780460358,
        0.46542122960090637,
        0.5249999761581421
      ],
      "material": "rubber",
      "color": "red",
      "size": "medium",
      "rotation": 147.4821751867454,
      "pixel_coords": [
        168,
        98,
        10.722704887390137
      ]
    }
  ],
  "image_filename": "CLEVR_new_000828.png",
  "image_index": 828,
  "directions": {
    "above": [
      0.0,
      0.0,
      1.0
    ],
    "front": [
      0.754490315914154,
      -0.6563112735748291,
      -0.0
    ],
    "left": [
      -0.6563112735748291,
      -0.7544902563095093,
      0.0
    ],
    "right": [
      0.6563112735748291,
      0.7544902563095093,
      -0.0
    ],
    "behind": [
      -0.754490315914154,
      0.6563112735748291,
      0.0
    ],
    "below": [
      -0.0,
      -0.0,
      -1.0
    ]
  }
}