{
  "relationships": {
    "front": [
      [
        1,
        3
      ],
      [
        3
      ],
      [
        0,
        1,
        3,
        5
      ],
      [],
      [
        0,
        1,
        2,
        3,
        5
      ],
      [
        0,
        1,
        3
      ]
    ],
    "right": [
      [],
      [
        0,
        4
      ],
      [
        0,
        1,
        3,
        4,
        5
      ],
      [
        0,
        1,
        4
      ],
      [
        0
      ],
      [
        0,
        1,
        3,
        4
      ]
    ],
    "left": [
      [
        1,
        2,
        3,
        4,
        5
      ],
      [
        2,
        3,
        5
      ],
      [],
      [
        2,
        5
      ],
      [
        1,
        2,
        3,
        5
      ],
      [
        2
      ]
    ],
    "behind": [
      [
        2,
        4,
        5
      ],
      [
        0,
        2,
        4,
        5
      ],
      [
        4
      ],
      [
        0,
        1,
        2,
        4,
        5
      ],
      [],
      [
        2,
        4
      ]
    ]
  },
  "intruder_pos": [
    [
      100,
      125
    ],
    [
      119,
      144
    ]
  ],
  "image_filename": "CLEVR_new_001252.png",
  "directions": {
    "below": [
      -0.0,
      -0.0,
      -1.0
    ],
    "right": [
      0.6563112735748291,
      0.7544902563095093,
      -0.0
    ],
    "behind": [
      -0.754490315914154,
      0.6563112735748291,
      0.0
    ],
    "front": [
      0.754490315914154,
      -0.6563112735748291,
      -0.0
    ],
    "above": [
      0.0,
      0.0,
      1.0
    ],
    "left": [
      -0.6563112735748291,
      -0.7544902563095093,
      0.0
    ]
  },
  "image_index": 1252,
  "split": "new",
  "objects": [
    {
      "3d_coords": [
        2.127755641937256,
        0.9364497065544128,
        0.699999988079071
      ],
      "pixel_coords": [
        229,
        116,
        10.59997272491455
      ],
      "material": "rubber",
      "rotation": 263.8410020918218,
      "shape": "cube",
      "color": "red",
      "size": "large"
    },
    {
      "3d_coords": [
        2.238142728805542,
        -1.1311769485473633,
        0.3499999940395355
      ],
      "pixel_coords": [
        183,
        152,
        9.506303787231445
      ],
      "material": "rubber",
      "rotation": 354.7918751036117,
      "shape": "cube",
      "color": "green",
      "size": "small"
    },
    {
      "3d_coords": [
        -2.515285015106201,
        -0.6279687881469727,
        0.5249999761581421
      ],
      "pixel_coords": [
        102,
        88,
        12.849226951599121
      ],
      "material": "rubber",
      "rotation": 225.3471167075683,
      "shape": "cube",
      "color": "green",
      "size": "medium"
    },
    {
      "3d_coords": [
        2.286543130874634,
        -2.8347458839416504,
        0.3499999940395355
      ],
      "pixel_coords": [
        134,
        179,
        8.494060516357422
      ],
      "material": "rubber",
      "rotation": 314.43710624643296,
      "shape": "cube",
      "color": "red",
      "size": "small"
    },
    {
      "3d_coords": [
        -1.0152884721755981,
        2.3125405311584473,
        0.3499999940395355
      ],
      "pixel_coords": [
        188,
        84,
        13.635608673095703
      ],
      "material": "rubber",
      "rotation": 174.0578212132984,
      "shape": "cube",
      "color": "blue",
      "size": "small"
    },
    {
      "3d_coords": [
        -1.4391893148422241,
        -1.01142156124115,
        0.3499999940395355
      ],
      "pixel_coords": [
        110,
        105,
        12.002711296081543
      ],
      "material": "rubber",
      "rotation": 107.98096913328351,
      "shape": "sphere",
      "color": "green",
      "size": "small"
    }
  ]
}