{
  "split": "new",
  "intruder_pos": [
    [
      111,
      143
    ],
    [
      148,
      180
    ]
  ],
  "relationships": {
    "front": [
      [
        2,
        3,
        4
      ],
      [
        0,
        2,
        3,
        4,
        5
      ],
      [
        4
      ],
      [
        2,
        4
      ],
      [],
      [
        0,
        2,
        3,
        4
      ]
    ],
    "left": [
      [],
      [
        0,
        2,
        3,
        4,
        5
      ],
      [
        0,
        3,
        4,
        5
      ],
      [
        0
      ],
      [
        0,
        3,
        5
      ],
      [
        0,
        3
      ]
    ],
    "behind": [
      [
        1,
        5
      ],
      [],
      [
        0,
        1,
        3,
        5
      ],
      [
        0,
        1,
        5
      ],
      [
        0,
        1,
        2,
        3,
        5
      ],
      [
        1
      ]
    ],
    "right": [
      [
        1,
        2,
        3,
        4,
        5
      ],
      [],
      [
        1
      ],
      [
        1,
        2,
        4,
        5
      ],
      [
        1,
        2
      ],
      [
        1,
        2,
        4
      ]
    ]
  },
  "directions": {
    "front": [
      0.754490315914154,
      -0.6563112735748291,
      -0.0
    ],
    "above": [
      0.0,
      0.0,
      1.0
    ],
    "behind": [
      -0.754490315914154,
      0.6563112735748291,
      0.0
    ],
    "below": [
      -0.0,
      -0.0,
      -1.0
    ],
    "right": [
      0.6563112735748291,
      0.7544902563095093,
      -0.0
    ],
    "left": [
      -0.6563112735748291,
      -0.7544902563095093,
      0.0
    ]
  },
  "image_index": 22,
  "image_filename": "CLEVR_new_000022.png",
  "objects": [
    {
      "pixel_coords": [
        69,
        99,
        11.683259963989258
      ],
      "rotation": 129.93333989785958,
      "material": "rubber",
      "size": "medium",
      "shape": "cube",
      "color": "red",
      "3d_coords": [
        -2.3690950870513916,
        -1.9711768627166748,
        0.5249999761581421
      ]
    },
    {
      "pixel_coords": [
        185,
        74,
        13.845850944519043
      ],
      "rotation": 304.2053426905965,
      "material": "rubber",
      "size": "medium",
      "shape": "cube",
      "color": "green",
      "3d_coords": [
        -1.5960980653762817,
        2.6628172397613525,
        0.5249999761581421
      ]
    },
    {
      "pixel_coords": [
        178,
        128,
        9.884289741516113
      ],
      "rotation": 164.6625506978278,
      "material": "rubber",
      "size": "medium",
      "shape": "cube",
      "color": "green",
      "3d_coords": [
        1.4799416065216064,
        -0.5858863592147827,
        0.5249999761581421
      ]
    },
    {
      "pixel_coords": [
        99,
        122,
        10.556405067443848
      ],
      "rotation": 66.36710013815426,
      "material": "rubber",
      "size": "small",
      "shape": "cube",
      "color": "blue",
      "3d_coords": [
        -0.5613880157470703,
        -1.9447376728057861,
        0.3499999940395355
      ]
    },
    {
      "pixel_coords": [
        139,
        177,
        7.519560813903809
      ],
      "rotation": 154.87020508715662,
      "material": "rubber",
      "size": "large",
      "shape": "cube",
      "color": "green",
      "3d_coords": [
        2.79569411277771,
        -2.9946091175079346,
        0.699999988079071
      ]
    },
    {
      "pixel_coords": [
        130,
        78,
        12.993339538574219
      ],
      "rotation": 61.452517841079924,
      "material": "rubber",
      "size": "large",
      "shape": "sphere",
      "color": "green",
      "3d_coords": [
        -2.296065092086792,
        0.5125331878662109,
        0.699999988079071
      ]
    }
  ]
}